AUTHORS.txt
CHANGELOG.txt
INSTALL.txt
LICENSE.txt
MANIFEST
MANIFEST.in
README.txt
deploy.py
ez_setup.py
nik2img.py
setup.py
nik2img.egg-info/PKG-INFO
nik2img.egg-info/SOURCES.txt
nik2img.egg-info/dependency_links.txt
nik2img.egg-info/not-zip-safe
nik2img.egg-info/top_level.txt
tests/__init__.py
tests/mapfile_lambert.xml
tests/mapfile_wgs84.xml
tests/tests.py
tests/us_states_lambert.dbf
tests/us_states_lambert.prj
tests/us_states_lambert.shp
tests/us_states_lambert.shx
tests/us_states_wgs84.dbf
tests/us_states_wgs84.prj
tests/us_states_wgs84.shp
tests/us_states_wgs84.shx
tests/using_nik2img.txt
