Metadata-Version: 1.1
Name: nik2img
Version: 0.2.2
Summary: A mapfile to image converter for the Mapnik C++/Python mapping toolkit
Home-page: http://mapnik-utils.googlecode.com/
Author: Dane Springmeyer
Author-email: dbsgeo@gmail.com
License: GPLv2
Keywords: Mapnik,gis,geospatial
Platform: OS Independent
Classifier: Development Status :: 5 - Production/Stable
Classifier: Environment :: Console
Classifier: Environment :: Web Environment
Classifier: Intended Audience :: End Users/Desktop
Classifier: Intended Audience :: Developers
Classifier: Intended Audience :: Science/Research
Classifier: Operating System :: OS Independent
Classifier: Programming Language :: Python
Classifier: Topic :: Internet :: WWW/HTTP :: Dynamic Content
Classifier: Topic :: Utilities
Requires: Mapnik
